fanfou/__init__.py
fanfou/api.py
fanfou/auth.py
fanfou/photo.py
fanfou-0.2.6.dist-info/DESCRIPTION.rst
fanfou-0.2.6.dist-info/METADATA
fanfou-0.2.6.dist-info/RECORD
fanfou-0.2.6.dist-info/WHEEL
fanfou-0.2.6.dist-info/metadata.json
fanfou-0.2.6.dist-info/top_level.txt
