Metadata-Version: 2.0
Name: fanfou
Version: 0.2.6
Summary: OAuth of Fanfou
Home-page: http://github.com/akgnah/fanfou-py
Author: Akgnah
Author-email: 1024@setq.me
License: MIT
Keywords: fanfou oauth
Platform: any
Requires-Dist: six
